[
  {
    "id": 1,
    "nombreUsuario": "Test",
    "apellidoUsuario": "test",
    "email": "paularassiga@gmail.com",
    "pasword": "$2a$10$1NPM0h.8mdEMg6uazDw4LOW2aMiCn0iAIyBpHxQj8yLtdUyG.pGwe",
    "avatar": "1616457547249_img_.png",
    "user": 5
  },
  {
    "id": 2,
    "nombreUsuario": "test",
    "apellidoUsuario": "test",
    "email": "test@test.com.ar",
    "password": "$2a$10$zdsE8E.H9NPjg8gwDvJlMu344Gjt.uWCZXZnpl1/zRoH8ofYaq09C",
    "avatar": "1616457727031_img_.png",
    "user": 5
  },
  {
    "id": 3,
    "nombreUsuario": "Paula",
    "apellidoUsuario": "Rassiga",
    "email": "paularassiga@gjsdjg",
    "password": "$2a$10$aikcIOJQChVE/o8NIFszzOCNQlreGdXyp.qaAy4SiVdIILO2JZt52",
    "avatar": "1616459469756_img_.png",
    "user": 2
  },
  {
    "id": 4,
    "nombreUsuario": "test",
    "apellidoUsuario": "test",
    "email": "test@test.com",
    "password": "$2a$10$mxi5odPeVmujM3uqfDiI6uhPwNOKiwJsl5Puv7FSwWqXmypxYicce",
    "avatar": "1616542669819_img_.jpg",
    "user": 5
  },
  {
    "id": 5,
    "nombreUsuario": "Guillermo",
    "apellidoUsuario": "Rodriguez",
    "email": "guille@gmail.com",
    "password": "$2a$10$aE8DKuD2YtiI5Iw1C9sJ9uc3ffyqUJG3BtHpIXhMwsKm1XKq0//j6",
    "avatar": "1616621665262_img_.jpg"
  }
]